nester/__init__.py
nester/cli.py
nester/tui.py
nester/core/__init__.py
nester/core/commands.py
nester/core/nester_log.py
nester/core/utils.py
nester/core/templates/c/c_layout.json
nester/core/templates/cpp/cpp_layout.json
nester/core/templates/cs/cs_layout.json
nester/core/templates/java/java_layout.json
nester/core/templates/py/py_layout.json
nester/core/templates/rb/rb_layout.json
nester_struct-1.1.2.dist-info/LICENSE
nester_struct-1.1.2.dist-info/METADATA
nester_struct-1.1.2.dist-info/WHEEL
nester_struct-1.1.2.dist-info/entry_points.txt
nester_struct-1.1.2.dist-info/top_level.txt
nester_struct-1.1.2.dist-info/zip-safe
nester_struct-1.1.2.dist-info/RECORD
