Metadata-Version: 2.1
Name: nester-struct
Version: 1.1.2
Summary: Automated creation of project structure
Home-page: https://github.com/ByteOtter/nester
Author: Christopher Hock
Author-email: christopher-hock@protonmail.com
License: GPLv3.0
Keywords: automation,project_structure,python
Classifier: Natural Language :: English
Classifier: Operating System :: OS Independent
Classifier: Programming Language :: Python :: 3.10
Classifier: Programming Language :: Python :: 3.11
License-File: LICENSE
Requires-Dist: setuptools >=65.5.0
Requires-Dist: wheel >=0.37.1
Requires-Dist: click >=8.1.3
Requires-Dist: questionary >=1.10.0
Provides-Extra: dev
Requires-Dist: pre-commit ~=3.1.1 ; extra == 'dev'
Requires-Dist: isort ~=2.6.0 ; extra == 'dev'
Requires-Dist: black ~=23.1.0 ; extra == 'dev'
Requires-Dist: virtualenv ~=20.21.0 ; extra == 'dev'
Provides-Extra: docs
Requires-Dist: sphinx >=6.1.3 ; extra == 'docs'
Requires-Dist: sphinx-rtd-theme ; extra == 'docs'
Requires-Dist: towncrier ; extra == 'docs'
Provides-Extra: tests
Requires-Dist: pytest ~=7.2.2 ; extra == 'tests'
Requires-Dist: pytest-mock ; extra == 'tests'
Requires-Dist: pytest-cov ; extra == 'tests'
